LICENSE
MANIFEST.in
README.md
dependencies.txt
requirements.txt
setup.cfg
setup.py
django_mp_misc.egg-info/PKG-INFO
django_mp_misc.egg-info/SOURCES.txt
django_mp_misc.egg-info/dependency_links.txt
django_mp_misc.egg-info/requires.txt
django_mp_misc.egg-info/top_level.txt
misc/__init__.py
misc/constants.py
misc/middleware.py
misc/settings.py
misc/tests.py
misc/utils.py
misc/views.py
misc/locale/en/LC_MESSAGES/django.mo
misc/locale/en/LC_MESSAGES/django.po
misc/locale/ru/LC_MESSAGES/django.mo
misc/locale/ru/LC_MESSAGES/django.po
misc/locale/uk/LC_MESSAGES/django.mo
misc/locale/uk/LC_MESSAGES/django.po
misc/static/css/indents.css
misc/templates/error.html