Metadata-Version: 1.1
Name: django-mp-misc
Version: 1.7
Summary: Django misc apps
Home-page: https://github.com/pmaigutyak/mp-misc
Author: Paul Maigutyak
Author-email: pmaigutyak@gmail.com
License: MIT
Download-URL: https://github.com/pmaigutyak/mp-misc/archive/1.7.tar.gz
Platform: UNKNOWN
